dhgraph/__init__.py
dhgraph/dhgraph.py
dhgraph-1.0.0.dist-info/LICENSE
dhgraph-1.0.0.dist-info/METADATA
dhgraph-1.0.0.dist-info/WHEEL
dhgraph-1.0.0.dist-info/RECORD
