Metadata-Version: 2.1
Name: dhgraph
Version: 1.0.0
Summary: Python Module for Directed Hypergraphs
Home-page: https://github.com/toda-lab/dhgraph
License: MIT
Keywords: mathematics,hypergraph,directed hypergraph
Author: Takahisa Toda
Author-email: toda@disc.lab.uec.ac.jp
Requires-Python: >=3.8,<4.0
Classifier: Development Status :: 3 - Alpha
Classifier: Intended Audience :: Science/Research
Classifier: License :: OSI Approved :: MIT License
Classifier: Operating System :: OS Independent
Classifier: Programming Language :: Python
Classifier: Programming Language :: Python :: 3
Classifier: Programming Language :: Python :: 3.8
Classifier: Programming Language :: Python :: 3.9
Classifier: Programming Language :: Python :: 3.10
Classifier: Programming Language :: Python :: 3.11
Classifier: Programming Language :: Python :: 3 :: Only
Classifier: Topic :: Scientific/Engineering :: Artificial Intelligence
Classifier: Topic :: Scientific/Engineering :: Mathematics
Provides-Extra: test
Requires-Dist: graphviz (>=0.20.3,<0.21.0)
Requires-Dist: pytest (>=8.1.1,<9.0.0) ; extra == "test"
Project-URL: Documentation, https://dhgraph.readthedocs.io/en/latest/
Project-URL: Repository, https://github.com/toda-lab/dhgraph
